{
  "exercise": "Miniband Side Lying Clamshell",
  "exercise_en": "Miniband Side Lying Clamshell",
  "difficulty_level": "Débutant",
  "difficulty_level_en": "Beginner",
  "target_muscle_group": "Fessiers",
  "target_muscle_group_en": "Glutes",
  "primary_equipment": "Minibande",
  "primary_equipment_en": "Miniband",
  "posture": "Allongé sur le côté",
  "posture_en": "Side Lying",
  "single_or_double_arm": "Sans bras",
  "single_or_double_arm_en": "No Arms",
  "continuous_or_alternating_arms": "Continu",
  "continuous_or_alternating_arms_en": "Continuous",
  "grip": "Pas de prise",
  "grip_en": "No Grip",
  "continuous_or_alternating_legs": "Continu",
  "continuous_or_alternating_legs_en": "Continuous",
  "foot_elevation": "Pas de surélévation",
  "foot_elevation_en": "No Elevation",
  "combination_exercises": "Exercice isolé",
  "combination_exercises_en": "Single Exercise",
  "movement_pattern": "Rotation externe de la hanche",
  "movement_pattern_en": "Hip External Rotation",
  "body_region": "Bas du corps",
  "body_region_en": "Lower Body",
  "force_type": "Autre",
  "force_type_en": "Other",
  "mechanics": "Exercice d'isolation",
  "mechanics_en": "Isolation",
  "laterality": "Unilatéral",
  "laterality_en": "Unilateral",
  "primary_exercise_classification": "Musculation",
  "primary_exercise_classification_en": "Bodybuilding",
  "text": "Le Miniband Side Lying Clamshell est un exercice idéal pour les débutants souhaitant renforcer leurs fessiers de manière ciblée. Pour réaliser cet exercice, munissez-vous d'une minibande que vous placerez autour de vos cuisses, juste au-dessus des genoux. Allongez-vous sur le côté, en gardant votre corps bien aligné, sans utiliser vos bras pour vous soutenir. L'absence de prise est importante ici, car cet exercice est conçu pour isoler le bas du corps. \n\nLe mouvement consiste en une rotation externe de la hanche, où vous soulevez et abaissez vos jambes de manière continue, sans surélever vos pieds du sol. Cet exercice unilatéral se concentre sur le renforcement des muscles fessiers, tout en améliorant la stabilité et la mobilité de la région. En intégrant le Miniband Side Lying Clamshell dans votre routine de musculation, vous favoriserez le développement musculaire de votre bas du corps de manière efficace et sécurisée."
}