{
  "exercise": "Double Kettlebell Half Kneeling Overhead Press",
  "exercise_en": "Double Kettlebell Half Kneeling Overhead Press",
  "difficulty_level": "Novice",
  "difficulty_level_en": "Novice",
  "target_muscle_group": "Épaules",
  "target_muscle_group_en": "Shoulders",
  "primary_equipment": "Kettlebell",
  "primary_equipment_en": "Kettlebell",
  "posture": "À genoux sur une jambe",
  "posture_en": "Half Kneeling",
  "single_or_double_arm": "Deux bras",
  "single_or_double_arm_en": "Double Arm",
  "continuous_or_alternating_arms": "Continu",
  "continuous_or_alternating_arms_en": "Continuous",
  "grip": "Proné",
  "grip_en": "Pronated",
  "continuous_or_alternating_legs": "Continu",
  "continuous_or_alternating_legs_en": "Continuous",
  "foot_elevation": "Pas de surélévation",
  "foot_elevation_en": "No Elevation",
  "combination_exercises": "Exercice isolé",
  "combination_exercises_en": "Single Exercise",
  "movement_pattern": "Poussée verticale",
  "movement_pattern_en": "Vertical Push",
  "body_region": "Haut du corps",
  "body_region_en": "Upper Body",
  "force_type": "Poussée",
  "force_type_en": "Push",
  "mechanics": "Exercice composé",
  "mechanics_en": "Compound",
  "laterality": "Bilatéral",
  "laterality_en": "Bilateral",
  "primary_exercise_classification": "Musculation",
  "primary_exercise_classification_en": "Bodybuilding",
  "text": "Le Double Kettlebell Half Kneeling Overhead Press est un exercice de musculation idéal pour les novices qui souhaitent renforcer leurs épaules. Pour réaliser cet exercice, vous aurez besoin de deux kettlebells. Commencez en position à genoux sur une jambe, en gardant le tronc droit et les abdos engagés. Avec une prise pronée, soulevez simultanément les kettlebells au-dessus de votre tête en effectuant un mouvement de poussée verticale. Ce mouvement bilatéral permet de solliciter efficacement le haut du corps, en mettant l'accent sur les muscles des épaules. Les jambes restent au sol sans surélévation, ce qui stabilise votre posture tout au long de l'exercice. Le Double Kettlebell Half Kneeling Overhead Press est un exercice composé qui favorise le développement de la force de poussée, tout en améliorant la coordination et l'équilibre. Intégrez cet exercice isolé à votre routine pour optimiser votre entraînement de musculation !"
}