{
  "exercise": "Ring Bulgarian Row",
  "exercise_en": "Ring Bulgarian Row",
  "difficulty_level": "Novice",
  "difficulty_level_en": "Novice",
  "target_muscle_group": "Dos",
  "target_muscle_group_en": "Back",
  "primary_equipment": "Anneaux de gymnastique",
  "primary_equipment_en": "Gymnastic Rings",
  "posture": "Allongé sur le dos",
  "posture_en": "Supine",
  "single_or_double_arm": "Deux bras",
  "single_or_double_arm_en": "Double Arm",
  "continuous_or_alternating_arms": "Continu",
  "continuous_or_alternating_arms_en": "Continuous",
  "grip": "Proné",
  "grip_en": "Pronated",
  "continuous_or_alternating_legs": "Continu",
  "continuous_or_alternating_legs_en": "Continuous",
  "foot_elevation": "Pas de surélévation",
  "foot_elevation_en": "No Elevation",
  "combination_exercises": "Exercice isolé",
  "combination_exercises_en": "Single Exercise",
  "movement_pattern": "Tirage horizontal",
  "movement_pattern_en": "Horizontal Pull",
  "body_region": "Haut du corps",
  "body_region_en": "Upper Body",
  "force_type": "Tirage",
  "force_type_en": "Pull",
  "mechanics": "Exercice composé",
  "mechanics_en": "Compound",
  "laterality": "Bilatéral",
  "laterality_en": "Bilateral",
  "primary_exercise_classification": "Calisthénie",
  "primary_exercise_classification_en": "Calisthenics",
  "text": "Le Ring Bulgarian Row est un exercice de calisthénie de difficulté novice, idéal pour cibler les muscles du dos. Pour réaliser cet exercice, vous aurez besoin d'anneaux de gymnastique. Allongé sur le dos, vos bras doivent être en position pronée, agrippant les anneaux. L'exercice consiste en un tirage horizontal, où vous effectuez un mouvement continu avec vos bras, tout en maintenant les pieds au sol sans surélévation. Les jambes restent actives durant l'exercice, ce qui permet de stabiliser le corps et d'engager davantage les muscles du haut du corps. En tant qu'exercice composé, le Ring Bulgarian Row favorise le développement de la force de tirage de manière bilatérale, contribuant ainsi à un renforcement harmonieux du dos. Intégrez-le à votre routine pour améliorer votre force et votre stabilité!"
}