{
  "exercise": "Alternating Single Arm Dumbbell Pendlay Row",
  "exercise_en": "Alternating Single Arm Dumbbell Pendlay Row",
  "difficulty_level": "Novice",
  "difficulty_level_en": "Novice",
  "target_muscle_group": "Dos",
  "target_muscle_group_en": "Back",
  "primary_equipment": "Haltère",
  "primary_equipment_en": "Dumbbell",
  "posture": "Debout",
  "posture_en": "Standing",
  "single_or_double_arm": "Un bras",
  "single_or_double_arm_en": "Single Arm",
  "continuous_or_alternating_arms": "Alterné",
  "continuous_or_alternating_arms_en": "Alternating",
  "grip": "Neutre",
  "grip_en": "Neutral",
  "continuous_or_alternating_legs": "Continu",
  "continuous_or_alternating_legs_en": "Continuous",
  "foot_elevation": "Pas de surélévation",
  "foot_elevation_en": "No Elevation",
  "combination_exercises": "Exercice isolé",
  "combination_exercises_en": "Single Exercise",
  "movement_pattern": "Tirage horizontal",
  "movement_pattern_en": "Horizontal Pull",
  "body_region": "Haut du corps",
  "body_region_en": "Upper Body",
  "force_type": "Tirage",
  "force_type_en": "Pull",
  "mechanics": "Exercice composé",
  "mechanics_en": "Compound",
  "laterality": "Unilatéral",
  "laterality_en": "Unilateral",
  "primary_exercise_classification": "Musculation",
  "primary_exercise_classification_en": "Bodybuilding",
  "text": "L'Alternating Single Arm Dumbbell Pendlay Row est un excellent exercice de musculation, idéal pour les novices souhaitant renforcer leur dos. Cet exercice isolé se pratique debout, en utilisant un haltère. La prise est neutre, ce qui permet de cibler efficacement les muscles du haut du corps. \n\nLe mouvement, qui se fait de manière alternée avec un bras, implique un tirage horizontal qui sollicite principalement les muscles du dos tout en développant la force de tirage. Les jambes restent actives et en mouvement continu, sans surélévation des pieds, ce qui garantit une stabilité optimale tout au long de l'exercice. \n\nClassé comme un exercice composé et unilatéral, l'Alternating Single Arm Dumbbell Pendlay Row est parfait pour améliorer la force et l'équilibre musculaire, tout en intégrant une technique de tirage efficace. Ajoutez-le à votre routine pour un développement harmonieux de votre dos !"
}