{
  "exercise": "Double Kettlebell Floor Press",
  "exercise_en": "Double Kettlebell Floor Press",
  "difficulty_level": "Débutant",
  "difficulty_level_en": "Beginner",
  "target_muscle_group": "Poitrine",
  "target_muscle_group_en": "Chest",
  "primary_equipment": "Kettlebell",
  "primary_equipment_en": "Kettlebell",
  "posture": "Allongé sur le dos",
  "posture_en": "Supine",
  "single_or_double_arm": "Deux bras",
  "single_or_double_arm_en": "Double Arm",
  "continuous_or_alternating_arms": "Continu",
  "continuous_or_alternating_arms_en": "Continuous",
  "grip": "Proné",
  "grip_en": "Pronated",
  "continuous_or_alternating_legs": "Continu",
  "continuous_or_alternating_legs_en": "Continuous",
  "foot_elevation": "Pas de surélévation",
  "foot_elevation_en": "No Elevation",
  "combination_exercises": "Exercice isolé",
  "combination_exercises_en": "Single Exercise",
  "movement_pattern": "Poussée horizontale",
  "movement_pattern_en": "Horizontal Push",
  "body_region": "Haut du corps",
  "body_region_en": "Upper Body",
  "force_type": "Poussée",
  "force_type_en": "Push",
  "mechanics": "Exercice composé",
  "mechanics_en": "Compound",
  "laterality": "Bilatéral",
  "laterality_en": "Bilateral",
  "primary_exercise_classification": "Musculation",
  "primary_exercise_classification_en": "Bodybuilding",
  "text": "Le Double Kettlebell Floor Press est un exercice de musculation idéal pour les débutants souhaitant renforcer leur poitrine. Pour réaliser cet exercice, allongez-vous sur le dos, en prenant soin de maintenir vos jambes à plat sur le sol, sans surélévation des pieds. Tenez un kettlebell dans chaque main avec une prise pronée, les bras positionnés sur les côtés. En effectuant un mouvement de poussée horizontale, élevez les kettlebells vers le plafond en utilisant les deux bras de manière continue. Cette mécanique de mouvement bilatérale sollicite efficacement le haut du corps, en mettant l'accent sur les muscles de la poitrine. Le Double Kettlebell Floor Press, étant un exercice composé, permet de développer la force de poussée tout en maintenant une posture stable. Intégrez cet exercice isolé à votre routine pour améliorer votre force et votre endurance musculaire."
}