{
  "exercise": "Heavy Sandbag Bear Hug Alternating Cossack Squat",
  "exercise_en": "Heavy Sandbag Bear Hug Alternating Cossack Squat",
  "difficulty_level": "Intermédiaire",
  "difficulty_level_en": "Intermediate",
  "target_muscle_group": "Quadriceps",
  "target_muscle_group_en": "Quadriceps",
  "primary_equipment": "Sac de sable lourd",
  "primary_equipment_en": "Heavy Sandbag",
  "posture": "Debout",
  "posture_en": "Standing",
  "single_or_double_arm": "Deux bras",
  "single_or_double_arm_en": "Double Arm",
  "continuous_or_alternating_arms": "Continu",
  "continuous_or_alternating_arms_en": "Continuous",
  "grip": "Neutre",
  "grip_en": "Neutral",
  "continuous_or_alternating_legs": "Alterné",
  "continuous_or_alternating_legs_en": "Alternating",
  "foot_elevation": "Pas de surélévation",
  "foot_elevation_en": "No Elevation",
  "combination_exercises": "Exercice isolé",
  "combination_exercises_en": "Single Exercise",
  "movement_pattern": "Dominant du genou",
  "movement_pattern_en": "Knee Dominant",
  "body_region": "Bas du corps",
  "body_region_en": "Lower Body",
  "force_type": "Poussée",
  "force_type_en": "Push",
  "mechanics": "Exercice composé",
  "mechanics_en": "Compound",
  "laterality": "Unilatéral",
  "laterality_en": "Unilateral",
  "primary_exercise_classification": null,
  "text": "Le Heavy Sandbag Bear Hug Alternating Cossack Squat est un exercice intermédiaire idéal pour cibler les quadriceps tout en améliorant votre force et votre stabilité. Pour réaliser cet exercice, vous aurez besoin d'un sac de sable lourd que vous maintenez avec vos deux bras dans une prise neutre, serrant le sac contre votre poitrine. En position debout, commencez par plier un genou pour descendre en squat sur le côté, tout en gardant l'autre jambe tendue. Ce mouvement de squat est alterné, ce qui permet de travailler chaque côté de votre corps de manière unilatérale. Les pieds restent au sol sans surélévation, et l'accent est mis sur la poussée à travers le genou, ce qui en fait un exercice composé très efficace pour le bas du corps. Intégrez ce mouvement dans votre routine pour renforcer vos muscles et améliorer votre équilibre!"
}