{
  "exercise": "Dumbbell Crush Grip Seated Good Morning",
  "exercise_en": "Dumbbell Crush Grip Seated Good Morning",
  "difficulty_level": "Novice",
  "difficulty_level_en": "Novice",
  "target_muscle_group": "Dos",
  "target_muscle_group_en": "Back",
  "primary_equipment": "Haltère",
  "primary_equipment_en": "Dumbbell",
  "posture": "Assis",
  "posture_en": "Seated",
  "single_or_double_arm": "Deux bras",
  "single_or_double_arm_en": "Double Arm",
  "continuous_or_alternating_arms": "Continu",
  "continuous_or_alternating_arms_en": "Continuous",
  "grip": "Prise écrasante",
  "grip_en": "Crush Grip",
  "continuous_or_alternating_legs": "Continu",
  "continuous_or_alternating_legs_en": "Continuous",
  "foot_elevation": "Pas de surélévation",
  "foot_elevation_en": "No Elevation",
  "combination_exercises": "Exercice isolé",
  "combination_exercises_en": "Single Exercise",
  "movement_pattern": "Hinge de la hanche",
  "movement_pattern_en": "Hip Hinge",
  "body_region": null,
  "force_type": null,
  "mechanics": "Exercice composé",
  "mechanics_en": "Compound",
  "laterality": "Bilatéral",
  "laterality_en": "Bilateral",
  "primary_exercise_classification": "Musculation",
  "primary_exercise_classification_en": "Bodybuilding",
  "text": "L'exercice « Dumbbell Crush Grip Seated Good Morning » est une excellente option pour les novices souhaitant renforcer leur dos. Pour réaliser cet exercice, vous aurez besoin d'un haltère. Asseyez-vous sur un banc ou une surface stable, en adoptant une posture droite. Prenez l'haltère avec une prise écrasante, utilisant les deux bras pour maintenir une prise solide. Ce mouvement, qui se concentre sur un modèle de mouvement de hinge de la hanche, sollicite efficacement les muscles du dos tout en étant un exercice isolé. Pendant l'exécution, vos bras et vos jambes doivent effectuer un mouvement continu, sans surélévation des pieds, permettant ainsi de travailler en bilatéral. Cet exercice composé est idéal pour développer la force et la stabilité du dos, tout en étant accessible aux débutants. Intégrez-le à votre routine de musculation pour des résultats optimaux."
}