{
  "exercise": "Parallette Mountain Climber",
  "exercise_en": "Parallette Mountain Climber",
  "difficulty_level": "Novice",
  "difficulty_level_en": "Novice",
  "target_muscle_group": "Abdominaux",
  "target_muscle_group_en": "Abdominals",
  "primary_equipment": "Barres parallèles",
  "primary_equipment_en": "Parallette Bars",
  "posture": "Allongé sur le ventre",
  "posture_en": "Prone",
  "single_or_double_arm": "Deux bras",
  "single_or_double_arm_en": "Double Arm",
  "continuous_or_alternating_arms": "Continu",
  "continuous_or_alternating_arms_en": "Continuous",
  "grip": "Neutre",
  "grip_en": "Neutral",
  "continuous_or_alternating_legs": "Alterné",
  "continuous_or_alternating_legs_en": "Alternating",
  "foot_elevation": "Pas de surélévation",
  "foot_elevation_en": "No Elevation",
  "combination_exercises": "Exercice isolé",
  "combination_exercises_en": "Single Exercise",
  "movement_pattern": "Anti-extension",
  "movement_pattern_en": "Anti-Extension",
  "body_region": "Tronc",
  "body_region_en": "Midsection",
  "force_type": "Autre",
  "force_type_en": "Other",
  "mechanics": "Exercice composé",
  "mechanics_en": "Compound",
  "laterality": "Unilatéral",
  "laterality_en": "Unilateral",
  "primary_exercise_classification": "Calisthénie",
  "primary_exercise_classification_en": "Calisthenics",
  "text": "Le Parallette Mountain Climber est un exercice de calisthénie idéal pour les novices qui souhaitent renforcer leurs abdominaux tout en améliorant leur stabilité du tronc. Pour réaliser cet exercice, commencez par vous allonger sur le ventre, en vous appuyant sur deux barres parallèles. Adoptez une prise neutre avec vos bras, qui doivent être en mouvement continu pour maintenir l'engagement des muscles du tronc. Pendant que vous exécutez le mouvement, alternez le déplacement de vos jambes sans les surélever, ce qui permet de travailler en profondeur la musculature abdominale tout en adoptant un modèle de mouvement anti-extension. Bien qu'il s'agisse d'un exercice isolé, le Parallette Mountain Climber engage également d'autres groupes musculaires, ce qui en fait une excellente option pour développer votre force globale. C’est un exercice composé qui sollicite unilatéralement votre corps, parfait pour les débutants désireux d'améliorer leur force et leur coordination.",
  "antagonist_muscle_group": null,
  "secondary_muscle_groups": [
    "Épaules",
    "Quadriceps",
    "Fessiers"
  ],
  "exercise_family": "Compound"
}