{
  "exercise": "Double Dumbbell Sots Press",
  "exercise_en": "Double Dumbbell Sots Press",
  "difficulty_level": "Intermédiaire",
  "difficulty_level_en": "Intermediate",
  "target_muscle_group": "Épaules",
  "target_muscle_group_en": "Shoulders",
  "primary_equipment": "Haltère",
  "primary_equipment_en": "Dumbbell",
  "posture": "Debout",
  "posture_en": "Standing",
  "single_or_double_arm": "Deux bras",
  "single_or_double_arm_en": "Double Arm",
  "continuous_or_alternating_arms": "Continu",
  "continuous_or_alternating_arms_en": "Continuous",
  "grip": "Neutre",
  "grip_en": "Neutral",
  "continuous_or_alternating_legs": "Continu",
  "continuous_or_alternating_legs_en": "Continuous",
  "foot_elevation": "Pas de surélévation",
  "foot_elevation_en": "No Elevation",
  "combination_exercises": "Exercice isolé",
  "combination_exercises_en": "Single Exercise",
  "movement_pattern": "Poussée verticale",
  "movement_pattern_en": "Vertical Push",
  "body_region": "Haut du corps",
  "body_region_en": "Upper Body",
  "force_type": "Poussée",
  "force_type_en": "Push",
  "mechanics": "Exercice composé",
  "mechanics_en": "Compound",
  "laterality": "Bilatéral",
  "laterality_en": "Bilateral",
  "primary_exercise_classification": "Musculation",
  "primary_exercise_classification_en": "Bodybuilding",
  "text": "Le Double Dumbbell Sots Press est un exercice de musculation intermédiaire qui cible principalement les épaules. Réalisé en position debout, cet exercice utilise deux haltères, permettant un travail bilatéral des bras. La prise neutre que vous adoptez vous offre une meilleure stabilité tout au long du mouvement. \n\nLe Double Dumbbell Sots Press se caractérise par un mouvement continu des bras, où vous effectuez une poussée verticale tout en maintenant une posture stable, sans surélever les pieds. Ce modèle de mouvement est considéré comme un exercice composé, car il sollicite plusieurs groupes musculaires en même temps tout en mettant l'accent sur la force de poussée. En intégrant cet exercice à votre routine de fitness, vous améliorerez non seulement la force de votre haut du corps, mais également votre coordination et votre équilibre.",
  "antagonist_muscle_group": "Trapeze inférieur",
  "secondary_muscle_groups": [
    "Jambes",
    "Core"
  ],
  "exercise_family": "Compound"
}