{
  "exercise": "Ring L Sit Archer Pull Up",
  "exercise_en": "Ring L Sit Archer Pull Up",
  "difficulty_level": "Expert",
  "difficulty_level_en": "Expert",
  "target_muscle_group": "Dos",
  "target_muscle_group_en": "Back",
  "primary_equipment": "Anneaux de gymnastique",
  "primary_equipment_en": "Gymnastic Rings",
  "posture": "Suspendu",
  "posture_en": "Hanging",
  "single_or_double_arm": "Deux bras",
  "single_or_double_arm_en": "Double Arm",
  "continuous_or_alternating_arms": "Alterné",
  "continuous_or_alternating_arms_en": "Alternating",
  "grip": "Proné",
  "grip_en": "Pronated",
  "continuous_or_alternating_legs": "Continu",
  "continuous_or_alternating_legs_en": "Continuous",
  "foot_elevation": "Pas de surélévation",
  "foot_elevation_en": "No Elevation",
  "combination_exercises": "Exercice isolé",
  "combination_exercises_en": "Single Exercise",
  "movement_pattern": "Tirage vertical",
  "movement_pattern_en": "Vertical Pull",
  "body_region": "Haut du corps",
  "body_region_en": "Upper Body",
  "force_type": "Tirage",
  "force_type_en": "Pull",
  "mechanics": "Exercice composé",
  "mechanics_en": "Compound",
  "laterality": "Unilatéral",
  "laterality_en": "Unilateral",
  "primary_exercise_classification": "Calisthénie",
  "primary_exercise_classification_en": "Calisthenics",
  "text": "Le Ring L Sit Archer Pull Up est un exercice de calisthénie de niveau expert, idéal pour renforcer le haut du corps, en particulier les muscles du dos. Pour réaliser cet exercice, vous aurez besoin d'anneaux de gymnastique, qui permettent une grande amplitude de mouvement et une meilleure activation musculaire. \n\nLa posture de départ est suspendue, avec les bras tendus et une prise pronée, engageant à la fois les biceps et les muscles du dos. Le mouvement s'effectue de manière alternée, tirant un bras à la fois tout en maintenant une position stable des jambes, sans surélévation des pieds. Ce tirage vertical se concentre sur une mécanique unilatérale, ce qui permet de travailler chaque côté de manière isolée. En intégrant le Ring L Sit Archer Pull Up à votre routine, vous développerez non seulement la force de tirage, mais aussi la stabilité et la coordination.",
  "antagonist_muscle_group": "Pectoraux",
  "secondary_muscle_groups": [
    "Épaules",
    "Abdominaux",
    "Avant-bras"
  ],
  "exercise_family": "Pull"
}