{
  "exercise": "Double Kettlebell Front Rack Alternating Lateral Lunge",
  "exercise_en": "Double Kettlebell Front Rack Alternating Lateral Lunge",
  "difficulty_level": "Novice",
  "difficulty_level_en": "Novice",
  "target_muscle_group": "Quadriceps",
  "target_muscle_group_en": "Quadriceps",
  "primary_equipment": "Kettlebell",
  "primary_equipment_en": "Kettlebell",
  "posture": "Debout",
  "posture_en": "Standing",
  "single_or_double_arm": "Deux bras",
  "single_or_double_arm_en": "Double Arm",
  "continuous_or_alternating_arms": "Continu",
  "continuous_or_alternating_arms_en": "Continuous",
  "grip": "Neutre",
  "grip_en": "Neutral",
  "continuous_or_alternating_legs": "Alterné",
  "continuous_or_alternating_legs_en": "Alternating",
  "foot_elevation": "Pas de surélévation",
  "foot_elevation_en": "No Elevation",
  "combination_exercises": "Exercice isolé",
  "combination_exercises_en": "Single Exercise",
  "movement_pattern": "Dominant du genou",
  "movement_pattern_en": "Knee Dominant",
  "body_region": "Bas du corps",
  "body_region_en": "Lower Body",
  "force_type": "Poussée",
  "force_type_en": "Push",
  "mechanics": "Exercice composé",
  "mechanics_en": "Compound",
  "laterality": "Unilatéral",
  "laterality_en": "Unilateral",
  "primary_exercise_classification": "Musculation",
  "primary_exercise_classification_en": "Bodybuilding",
  "text": "Le Double Kettlebell Front Rack Alternating Lateral Lunge est un exercice idéal pour les débutants souhaitant renforcer leurs quadriceps tout en améliorant leur stabilité et leur équilibre. Pour réaliser cet exercice, commencez par vous tenir debout, un kettlebell dans chaque main, en adoptant une prise neutre. Les bras, en position front rack, restent continuellement engagés tout au long du mouvement. \n\nL'exercice consiste à effectuer des fentes latérales alternées, ce qui signifie que vous déplacerez un pied sur le côté tout en pliant le genou, sans surélever les pieds. Ce mouvement est principalement dominé par le genou, mettant l'accent sur la force de poussée. En tant qu'exercice composé, il sollicite efficacement le bas du corps et favorise une latéralité unilatérale, essentielle pour un développement musculaire équilibré. En intégrant régulièrement le Double Kettlebell Front Rack Alternating Lateral Lunge dans votre routine de musculation, vous renforcerez non seulement vos quadriceps, mais améliorerez également votre coordination et votre puissance globale.",
  "antagonist_muscle_group": "Ischio-jambiers",
  "secondary_muscle_groups": [
    "Fessiers",
    "Adducteurs",
    "Mollets"
  ],
  "exercise_family": "Lunge"
}