{
  "exercise": "Single Arm Dumbbell Front Rack Cyclist Squat",
  "exercise_en": "Single Arm Dumbbell Front Rack Cyclist Squat",
  "difficulty_level": "Novice",
  "difficulty_level_en": "Novice",
  "target_muscle_group": "Quadriceps",
  "target_muscle_group_en": "Quadriceps",
  "primary_equipment": "Haltère",
  "primary_equipment_en": "Dumbbell",
  "posture": "Debout",
  "posture_en": "Standing",
  "single_or_double_arm": "Un bras",
  "single_or_double_arm_en": "Single Arm",
  "continuous_or_alternating_arms": "Continu",
  "continuous_or_alternating_arms_en": "Continuous",
  "grip": "Neutre",
  "grip_en": "Neutral",
  "continuous_or_alternating_legs": "Continu",
  "continuous_or_alternating_legs_en": "Continuous",
  "foot_elevation": "Talons surélevés",
  "foot_elevation_en": "Heels Elevated",
  "combination_exercises": "Exercice isolé",
  "combination_exercises_en": "Single Exercise",
  "movement_pattern": "Dominant du genou",
  "movement_pattern_en": "Knee Dominant",
  "body_region": "Bas du corps",
  "body_region_en": "Lower Body",
  "force_type": "Poussée",
  "force_type_en": "Push",
  "mechanics": "Exercice composé",
  "mechanics_en": "Compound",
  "laterality": "Unilatéral",
  "laterality_en": "Unilateral",
  "primary_exercise_classification": "Musculation",
  "primary_exercise_classification_en": "Bodybuilding",
  "text": "Le Single Arm Dumbbell Front Rack Cyclist Squat est un excellent exercice de musculation conçu pour les novices souhaitant cibler efficacement les quadriceps. Pour réaliser cet exercice, commencez par vous tenir debout en portant un haltère dans une prise neutre, avec un bras. La posture est essentielle : assurez-vous que votre dos est droit et vos pieds sont légèrement écartés. En gardant l'haltère en position de \"front rack\", effectuez un squat en faisant descendre vos hanches tout en maintenant un mouvement continu de vos bras. Les talons doivent rester surélevés pour accentuer la sollicitation des quadriceps. Cet exercice isolé, qui favorise un modèle de mouvement dominant du genou, est idéal pour développer la force de poussée dans le bas du corps. En étant unilatéral, il permet également d'améliorer votre équilibre et votre stabilité.",
  "antagonist_muscle_group": "Ischio-jambiers",
  "secondary_muscle_groups": [
    "Fessiers",
    "Core"
  ],
  "exercise_family": "Compound"
}