{
  "exercise": "Bar Strict Muscle Up",
  "exercise_en": "Bar Strict Muscle Up",
  "difficulty_level": "Expert",
  "difficulty_level_en": "Expert",
  "target_muscle_group": "Dos",
  "target_muscle_group_en": "Back",
  "primary_equipment": "Barre de traction",
  "primary_equipment_en": "Pull Up Bar",
  "posture": "Suspendu",
  "posture_en": "Hanging",
  "single_or_double_arm": "Deux bras",
  "single_or_double_arm_en": "Double Arm",
  "continuous_or_alternating_arms": "Continu",
  "continuous_or_alternating_arms_en": "Continuous",
  "grip": "Prise fausse",
  "grip_en": "False Grip",
  "continuous_or_alternating_legs": "Continu",
  "continuous_or_alternating_legs_en": "Continuous",
  "foot_elevation": "Pas de surélévation",
  "foot_elevation_en": "No Elevation",
  "combination_exercises": "Exercice isolé",
  "combination_exercises_en": "Single Exercise",
  "movement_pattern": "Tirage vertical",
  "movement_pattern_en": "Vertical Pull",
  "body_region": "Haut du corps",
  "body_region_en": "Upper Body",
  "force_type": "Poussée et Tirage",
  "force_type_en": "Push & Pull",
  "mechanics": "Exercice composé",
  "mechanics_en": "Compound",
  "laterality": "Bilatéral",
  "laterality_en": "Bilateral",
  "primary_exercise_classification": "Calisthénie",
  "primary_exercise_classification_en": "Calisthenics",
  "text": "Le Bar Strict Muscle Up est un exercice de calisthénie de difficulté expert, idéal pour cibler principalement les muscles du dos tout en sollicitant l'ensemble du haut du corps. Pour réaliser ce mouvement, vous aurez besoin d'une barre de traction. Commencez par vous suspendre à la barre avec une prise fausse, en utilisant vos deux bras pour garantir une meilleure stabilité et un contrôle optimal. \n\nLe mouvement consiste en un tirage vertical continu, où vous devez maintenir une posture suspendue sans surélever les jambes. Les bras travaillent en synergie, combinant des mouvements de poussée et de tirage, ce qui en fait un exercice composé et bilatéral. En pratiquant le Bar Strict Muscle Up, vous développerez non seulement votre force, mais également votre technique et votre coordination. C'est un exercice isolé qui demande une grande maîtrise, parfait pour les athlètes souhaitant relever un défi de taille dans leur routine d'entraînement.",
  "antagonist_muscle_group": "Pectoraux",
  "secondary_muscle_groups": [
    "Épaules",
    "Biceps",
    "Abdominaux"
  ],
  "exercise_family": "Compound"
}