{
  "exercise": "Clubbell Side to Side Swing",
  "exercise_en": "Clubbell Side to Side Swing",
  "difficulty_level": "Intermédiaire",
  "difficulty_level_en": "Intermediate",
  "target_muscle_group": "Abdominaux",
  "target_muscle_group_en": "Abdominals",
  "primary_equipment": "Clubbell",
  "primary_equipment_en": "Clubbell",
  "posture": "Debout",
  "posture_en": "Standing",
  "single_or_double_arm": "Deux bras",
  "single_or_double_arm_en": "Double Arm",
  "continuous_or_alternating_arms": "Continu",
  "continuous_or_alternating_arms_en": "Continuous",
  "grip": "Neutre",
  "grip_en": "Neutral",
  "continuous_or_alternating_legs": "Continu",
  "continuous_or_alternating_legs_en": "Continuous",
  "foot_elevation": "Pas de surélévation",
  "foot_elevation_en": "No Elevation",
  "combination_exercises": "Exercice isolé",
  "combination_exercises_en": "Single Exercise",
  "movement_pattern": "Rotationnel",
  "movement_pattern_en": "Rotational",
  "body_region": "Corps entier",
  "body_region_en": "Full Body",
  "force_type": "Autre",
  "force_type_en": "Other",
  "mechanics": "Exercice composé",
  "mechanics_en": "Compound",
  "laterality": "Bilatéral",
  "laterality_en": "Bilateral",
  "primary_exercise_classification": "Ballistiques",
  "primary_exercise_classification_en": "Ballistics",
  "text": "Le Clubbell Side to Side Swing est un exercice intermédiaire qui cible principalement les abdominaux tout en sollicitant également l'ensemble du corps. Pour réaliser cet exercice, vous aurez besoin d'un clubbell, un équipement particulièrement utile pour développer la force fonctionnelle. \n\nAdoptez une posture debout, en tenant le clubbell avec les deux bras dans une prise neutre. Le mouvement consiste à balancer le clubbell de gauche à droite de manière continue, ce qui crée un modèle de mouvement rotationnel. Vos jambes restent en mouvement continu, sans surélévation des pieds, ce qui permet une stabilité optimale. \n\nCet exercice isolé est classé parmi les exercices ballistiques et constitue un entraînement composé qui favorise le développement de la force latérale. En intégrant le Clubbell Side to Side Swing dans votre routine, vous renforcerez non seulement vos abdominaux, mais aussi votre coordination et votre endurance.",
  "antagonist_muscle_group": null,
  "secondary_muscle_groups": [
    "Obliques",
    "Épaules",
    "Dorsaux",
    "Jambes"
  ],
  "exercise_family": "Compound"
}