{
  "exercise": "Bodyweight Wall Supported Tibialis Raise",
  "exercise_en": "Bodyweight Wall Supported Tibialis Raise",
  "difficulty_level": "Débutant",
  "difficulty_level_en": "Beginner",
  "target_muscle_group": "Tibias",
  "target_muscle_group_en": "Shins",
  "primary_equipment": "Poids du corps",
  "primary_equipment_en": "Bodyweight",
  "posture": "Debout",
  "posture_en": "Standing",
  "single_or_double_arm": "Sans bras",
  "single_or_double_arm_en": "No Arms",
  "continuous_or_alternating_arms": "Continu",
  "continuous_or_alternating_arms_en": "Continuous",
  "grip": "Pas de prise",
  "grip_en": "No Grip",
  "continuous_or_alternating_legs": "Continu",
  "continuous_or_alternating_legs_en": "Continuous",
  "foot_elevation": "Pas de surélévation",
  "foot_elevation_en": "No Elevation",
  "combination_exercises": "Exercice isolé",
  "combination_exercises_en": "Single Exercise",
  "movement_pattern": "Dorsiflexion de la cheville",
  "movement_pattern_en": "Ankle Dorsiflexion",
  "body_region": "Bas du corps",
  "body_region_en": "Lower Body",
  "force_type": null,
  "mechanics": "Exercice d'isolation",
  "mechanics_en": "Isolation",
  "laterality": "Unilatéral",
  "laterality_en": "Unilateral",
  "primary_exercise_classification": null,
  "text": "Le Bodyweight Wall Supported Tibialis Raise est un excellent exercice pour les débutants, ciblant spécifiquement les muscles tibiaux de la partie inférieure du corps. Cet exercice se pratique debout, sans besoin d'équipement, utilisant uniquement le poids de votre corps. En vous appuyant contre un mur pour maintenir votre équilibre, vous pouvez concentrer votre attention sur le mouvement de vos jambes, qui doit être continu et fluide.\n\nL'exercice implique une dorsiflexion de la cheville, permettant d'isoler les muscles tibiaux de manière efficace. Il est important de noter que cet exercice est unilatéral, ce qui signifie que vous travaillerez un côté à la fois, favorisant ainsi l'équilibre musculaire. De plus, il n'y a pas de surélévation des pieds, ce qui rend le Bodyweight Wall Supported Tibialis Raise accessible à tous. En intégrant cet exercice à votre routine, vous renforcerez non seulement vos tibias, mais améliorerez également votre stabilité et votre contrôle corporel.",
  "antagonist_muscle_group": "Gastrocnémien",
  "secondary_muscle_groups": [],
  "exercise_family": "Isolation"
}