{
  "exercise": "Bulgarian Bag Alternating Spin",
  "exercise_en": "Bulgarian Bag Alternating Spin",
  "difficulty_level": "Avancé",
  "difficulty_level_en": "Advanced",
  "target_muscle_group": "Épaules",
  "target_muscle_group_en": "Shoulders",
  "primary_equipment": "Sac bulgare",
  "primary_equipment_en": "Bulgarian Bag",
  "posture": "Debout",
  "posture_en": "Standing",
  "single_or_double_arm": "Deux bras",
  "single_or_double_arm_en": "Double Arm",
  "continuous_or_alternating_arms": "Continu",
  "continuous_or_alternating_arms_en": "Continuous",
  "grip": "Neutre",
  "grip_en": "Neutral",
  "continuous_or_alternating_legs": "Continu",
  "continuous_or_alternating_legs_en": "Continuous",
  "foot_elevation": "Pas de surélévation",
  "foot_elevation_en": "No Elevation",
  "combination_exercises": "Exercice isolé",
  "combination_exercises_en": "Single Exercise",
  "movement_pattern": "Rotationnel",
  "movement_pattern_en": "Rotational",
  "body_region": "Haut du corps",
  "body_region_en": "Upper Body",
  "force_type": "Tirage",
  "force_type_en": "Pull",
  "mechanics": "Exercice composé",
  "mechanics_en": "Compound",
  "laterality": "Bilatéral",
  "laterality_en": "Bilateral",
  "primary_exercise_classification": null,
  "text": "L'exercice appelé \"Bulgarian Bag Alternating Spin\" est un mouvement avancé qui cible principalement les épaules, tout en engageant d'autres muscles du haut du corps. Pour réaliser cet exercice, vous aurez besoin d'un sac bulgare. Positionnez-vous debout avec une prise neutre sur le sac, en utilisant vos deux bras pour effectuer un mouvement de rotation continu. Ce mouvement dynamique ne nécessite pas de surélévation des pieds, ce qui permet de maintenir une stabilité optimale. L'exercice est bilatéral, impliquant les deux côtés du corps de manière harmonieuse. En raison de son modèle de mouvement rotationnel, le Bulgarian Bag Alternating Spin constitue un exercice isolé de tirage qui sollicite également votre force et votre coordination. C'est un excellent moyen de renforcer vos épaules tout en développant votre puissance fonctionnelle.",
  "antagonist_muscle_group": null,
  "secondary_muscle_groups": [
    "Dos",
    "Triceps",
    "Abdominaux"
  ],
  "exercise_family": "Compound"
}