{
  "id": "ex_0610_Superband_Single_Leg_Standing_Bent_Knee_Hip_External_Rotation",
  "text": "Cet exercice consiste à effectuer une rotation externe de la hanche tout en se tenant sur une jambe, en utilisant une superband pour ajouter de la résistance. Il cible principalement les muscles fessiers et est idéal pour renforcer le bas du corps.",
  "title": "Rotation externe de la hanche en position debout sur une jambe avec superband",
  "category": "exercice",
  "type": "renforcement",
  "level": "débutant"
}