{
  "id": "ex_2041_Single_Arm_Dumbbell_Floor_Press",
  "text": "Le développé couché avec haltère à un bras est un exercice de renforcement qui cible principalement les muscles de la poitrine. Il se pratique au sol avec un haltère et fait partie des mouvements de musculation de type composé, impliquant plusieurs groupes musculaires. Cet exercice est idéal pour les débutants souhaitant développer leur force dans le haut du corps.",
  "title": "Développé couché avec haltère à un bras",
  "category": "exercice",
  "type": "renforcement",
  "level": "débutant"
}