{
  "id": "ex_2802_Single_Arm_Kettlebell_Bottoms_Up_Overhead_Contralateral_Forward_Lunge",
  "text": "Cet exercice consiste à effectuer une fente avant tout en tenant un kettlebell à une main, placé en position inversée au-dessus de la tête. Il cible principalement les quadriceps et nécessite une bonne maîtrise des mouvements de renforcement musculaire.",
  "title": "Fente avant contralatérale avec kettlebell à une main en position inversée",
  "category": "exercice",
  "type": "renforcement",
  "level": "confirmé"
}