{
  "id": "f1ad515c-bd72-4fa0-adec-ee8094b67ebb",
  "text": "Exercise: Stability Ball V Up Pass\nDifficulty: Novice\nMuscles: Abdominals\nEquipment: Stability Ball\nMechanics: Compound\nBody Region: Midsection\nForce Type: Other\nClassification: Unsorted*",
  "metadata": {
    "difficulty_level": "Novice",
    "muscles": "Abdominals",
    "equipment": "Stability Ball",
    "mechanics": "Compound",
    "body_region": "Midsection",
    "force_type": "Other",
    "laterality": "Bilateral",
    "primary_exercise_classification": "Unsorted*"
  }
}