{
  "id": "8ec9142f-f7dd-4484-a229-41186075f4d1",
  "text": "Exercise: Slider Double Kettlebell Bottoms Up Front Rack Lateral Lunge\nDifficulty: Intermediate\nMuscles: Quadriceps\nEquipment: Sliders\nMechanics: Compound\nBody Region: Lower Body\nForce Type: Other\nClassification: Bodybuilding",
  "metadata": {
    "difficulty_level": "Intermediate",
    "muscles": "Quadriceps",
    "equipment": "Sliders",
    "mechanics": "Compound",
    "body_region": "Lower Body",
    "force_type": "Other",
    "laterality": "Unilateral",
    "primary_exercise_classification": "Bodybuilding"
  }
}