{
  "id": "f71d8ef6-7877-473b-80b5-fc6ab5ce1119",
  "text": "Exercise: Single Arm Kettlebell Overhead Press\nDifficulty: Novice\nMuscles: Shoulders\nEquipment: Kettlebell\nMechanics: Compound\nBody Region: Upper Body\nForce Type: Push\nClassification: Bodybuilding",
  "metadata": {
    "difficulty_level": "Novice",
    "muscles": "Shoulders",
    "equipment": "Kettlebell",
    "mechanics": "Compound",
    "body_region": "Upper Body",
    "force_type": "Push",
    "laterality": "Unilateral",
    "primary_exercise_classification": "Bodybuilding"
  }
}