{
  "id": "7d2d18b7-215a-407f-a17f-95659a16e269",
  "text": "Exercise: Kettlebell Bottoms Up Horn Grip Cyclist Squat\nDifficulty: Novice\nMuscles: Quadriceps\nEquipment: Kettlebell\nMechanics: Compound\nBody Region: Lower Body\nForce Type: Push\nClassification: Bodybuilding",
  "metadata": {
    "difficulty_level": "Novice",
    "muscles": "Quadriceps",
    "equipment": "Kettlebell",
    "mechanics": "Compound",
    "body_region": "Lower Body",
    "force_type": "Push",
    "laterality": "Bilateral",
    "primary_exercise_classification": "Bodybuilding"
  }
}