{
  "id": "0abc057a-a59f-4222-83e3-9d19cb21c96f",
  "text": "Exercise: Ring Circle Front Lever\nDifficulty: Expert\nMuscles: Abdominals\nEquipment: Gymnastic Rings\nMechanics: Compound\nBody Region: Midsection\nForce Type: Other\nClassification: Calisthenics",
  "metadata": {
    "difficulty_level": "Expert",
    "muscles": "Abdominals",
    "equipment": "Gymnastic Rings",
    "mechanics": "Compound",
    "body_region": "Midsection",
    "force_type": "Other",
    "laterality": "Bilateral",
    "primary_exercise_classification": "Calisthenics"
  }
}