{
  "id": "edebb676-576b-444b-b161-d1b1115a8171",
  "text": "Exercise: Ring Straddle L Sit\nDifficulty: Expert\nMuscles: Abdominals\nEquipment: Gymnastic Rings\nMechanics: Compound\nBody Region: Unsorted*\nForce Type: Other\nClassification: Calisthenics",
  "metadata": {
    "difficulty_level": "Expert",
    "muscles": "Abdominals",
    "equipment": "Gymnastic Rings",
    "mechanics": "Compound",
    "body_region": "Unsorted*",
    "force_type": "Other",
    "laterality": "Bilateral",
    "primary_exercise_classification": "Calisthenics"
  }
}