{
  "id": "596b94fe-14f8-4d03-8fa2-bd20fd24ae5d",
  "text": "Exercise: Double Kettlebell Bottoms Up Front Rack Low Switch Cossack Squat\nDifficulty: Advanced\nMuscles: Quadriceps\nEquipment: Kettlebell\nMechanics: Compound\nBody Region: Lower Body\nForce Type: Push\nClassification: Bodybuilding",
  "metadata": {
    "difficulty_level": "Advanced",
    "muscles": "Quadriceps",
    "equipment": "Kettlebell",
    "mechanics": "Compound",
    "body_region": "Lower Body",
    "force_type": "Push",
    "laterality": "Unilateral",
    "primary_exercise_classification": "Bodybuilding"
  }
}