{
  "id": "1f56c190-fb3b-44b5-99b1-514e790a9531",
  "text": "Exercise: Bar Chin Up\nDifficulty: Intermediate\nMuscles: Biceps\nEquipment: Pull Up Bar\nMechanics: Compound\nBody Region: Upper Body\nForce Type: Pull\nClassification: Calisthenics",
  "metadata": {
    "difficulty_level": "Intermediate",
    "muscles": "Biceps",
    "equipment": "Pull Up Bar",
    "mechanics": "Compound",
    "body_region": "Upper Body",
    "force_type": "Pull",
    "laterality": "Bilateral",
    "primary_exercise_classification": "Calisthenics"
  }
}