{
  "id": "09f6637b-2284-490d-9a6f-bf6489f7eeb5",
  "text": "Exercise: Bar Half Lay Back Lever\nDifficulty: Advanced\nMuscles: Abdominals\nEquipment: Pull Up Bar\nMechanics: Compound\nBody Region: Unsorted*\nForce Type: Other\nClassification: Calisthenics",
  "metadata": {
    "difficulty_level": "Advanced",
    "muscles": "Abdominals",
    "equipment": "Pull Up Bar",
    "mechanics": "Compound",
    "body_region": "Unsorted*",
    "force_type": "Other",
    "laterality": "Bilateral",
    "primary_exercise_classification": "Calisthenics"
  }
}