{
  "id": "71bf6ea1-877b-44a3-9b3a-70957113b42d",
  "text": "Exercise: Barbell Overhead Alternating Lateral Lunge\nDifficulty: Advanced\nMuscles: Quadriceps\nEquipment: Barbell\nMechanics: Compound\nBody Region: Lower Body\nForce Type: Push\nClassification: Bodybuilding",
  "metadata": {
    "difficulty_level": "Advanced",
    "muscles": "Quadriceps",
    "equipment": "Barbell",
    "mechanics": "Compound",
    "body_region": "Lower Body",
    "force_type": "Push",
    "laterality": "Unilateral",
    "primary_exercise_classification": "Bodybuilding"
  }
}